fellow_aiden/__init__.py
fellow_aiden/profile.py
fellow_aiden/schedule.py
fellow_aiden-0.2.2.dist-info/licenses/LICENSE
fellow_aiden-0.2.2.dist-info/METADATA
fellow_aiden-0.2.2.dist-info/WHEEL
fellow_aiden-0.2.2.dist-info/top_level.txt
fellow_aiden-0.2.2.dist-info/RECORD
