Metadata-Version: 2.4
Name: fellow-aiden
Version: 0.2.2
Summary: Interface for interacting with Fellow Aiden coffee brewer
Home-page: https://github.com/9b/fellow-aiden
Author: Brandon Dixon
Author-email: Brandon Dixon <brandon@9bplus.com>
License: GNUv3
Keywords: coffee,coffee brewer,fellow,coffee tech
Classifier: Development Status :: 4 - Beta
Classifier: Intended Audience :: Developers
Classifier: Natural Language :: English
Classifier: Programming Language :: Python
Classifier: Topic :: Software Development :: Libraries
License-File: LICENSE
Requires-Dist: requests>=2.32.3
Requires-Dist: pydantic>=2.10.4
Provides-Extra: dev
Requires-Dist: pytest>=6.2; extra == "dev"
Requires-Dist: black>=21.9b0; extra == "dev"
Dynamic: author
Dynamic: home-page
Dynamic: license-file
